mass_replace/__init__.py
mass_replace/__version__.py
mass_replace/mass_replace.py
mass_replace-0.0.3.dist-info/LICENSE
mass_replace-0.0.3.dist-info/METADATA
mass_replace-0.0.3.dist-info/WHEEL
mass_replace-0.0.3.dist-info/entry_points.txt
mass_replace-0.0.3.dist-info/top_level.txt
mass_replace-0.0.3.dist-info/RECORD
