Metadata-Version: 2.1
Name: mass-replace
Version: 0.0.3
Summary: Walkthrough directories and find and replace txt on select filetypes.
Home-page: https://github.com/Kilo59/mass_replace
Author: Gabriel Gore
Author-email: gabriel59kg@gmail.com
License: MIT
Platform: UNKNOWN
Classifier: License :: OSI Approved :: MIT License
Classifier: Programming Language :: Python
Classifier: Programming Language :: Python :: 3
Classifier: Programming Language :: Python :: 3.5
Classifier: Programming Language :: Python :: 3.6
Classifier: Programming Language :: Python :: 3.7
Classifier: Programming Language :: Python :: Implementation :: CPython
Classifier: Development Status :: 2 - Pre-Alpha
Requires-Python: >=3.5.0
Requires-Dist: pyaml
